ajchocoboo/BasicMath.py
ajchocoboo/Numbers.py
ajchocoboo/__init__.py
ajchocoboo-0.0.1.dist-info/METADATA
ajchocoboo-0.0.1.dist-info/WHEEL
ajchocoboo-0.0.1.dist-info/top_level.txt
ajchocoboo-0.0.1.dist-info/RECORD
