Metadata-Version: 2.1
Name: ajchocoboo
Version: 0.0.1
Summary: My first Python package
Home-page: UNKNOWN
Author: Asheesh Janda
Author-email: <asheeshdeep.janda@gmail.com>
License: UNKNOWN
Keywords: python,first lib
Platform: UNKNOWN
Classifier: Development Status :: 3 - Alpha
Classifier: Intended Audience :: Education
Classifier: Programming Language :: Python :: 2
Classifier: Programming Language :: Python :: 3
Classifier: Operating System :: MacOS :: MacOS X
Classifier: Operating System :: Microsoft :: Windows
Requires-Python: >=3.5
